MEDCNN/__init__.py
MEDCNN/models/ControlUnet2D.py
MEDCNN/models/G2DwithoutAttention.py
MEDCNN/utils/BoundaryAwareDiceLoss.py
MEDCNN/utils/Load2Ddata.py
MEDCNN/utils/TTViterators.py
MEDCNN/utils/Train1.py
MEDCNN/utils/compile1.py
MEDCNN/utils/dice.py
MEDCNN/utils/tf_select_a_gpu.py
MEDCNN/utils/utils.py
medcnn-0.0.2.dist-info/METADATA
medcnn-0.0.2.dist-info/WHEEL
medcnn-0.0.2.dist-info/licenses/LICENSE
medcnn-0.0.2.dist-info/RECORD
